{
  "swagger": "2.0",
  "info": {
    "title": "auth/v1/auth.proto",
    "version": "version not set"
  },
  "tags": [
    {
      "name": "AuthService"
    },
    {
      "name": "IAMService"
    }
  ],
  "consumes": [
    "application/json"
  ],
  "produces": [
    "application/json"
  ],
  "paths": {
    "/auth/v1/audit-logs": {
      "get": {
        "operationId": "AuthService_ListAuditLogs",
        "responses": {
          "200": {
            "description": "A successful response.",
            "schema": {
              "$ref": "#/definitions/authListAuditLogsResponse"
            }
          },
          "default": {
            "description": "An unexpected error response.",
            "schema": {
              "$ref": "#/definitions/rpcStatus"
            }
          }
        },
        "parameters": [
          {
            "name": "pageSize",
            "in": "query",
            "required": false,
            "type": "integer",
            "format": "int32"
          }
        ],
        "tags": [
          "AuthService"
        ]
      }
    },
    "/auth/v1/google/callback": {
      "get": {
        "operationId": "AuthService_GoogleCallback",
        "responses": {
          "200": {
            "description": "A successful response.",
            "schema": {
              "$ref": "#/definitions/authGoogleCallbackResponse"
            }
          },
          "default": {
            "description": "An unexpected error response.",
            "schema": {
              "$ref": "#/definitions/rpcStatus"
            }
          }
        },
        "parameters": [
          {
            "name": "state",
            "in": "query",
            "required": false,
            "type": "string"
          },
          {
            "name": "code",
            "in": "query",
            "required": false,
            "type": "string"
          }
        ],
        "tags": [
          "AuthService"
        ]
      }
    },
    "/auth/v1/google/exchange": {
      "post": {
        "operationId": "AuthService_ExchangeGoogleLogin",
        "responses": {
          "200": {
            "description": "A successful response.",
            "schema": {
              "$ref": "#/definitions/authLoginResponse"
            }
          },
          "default": {
            "description": "An unexpected error response.",
            "schema": {
              "$ref": "#/definitions/rpcStatus"
            }
          }
        },
        "parameters": [
          {
            "name": "body",
            "in": "body",
            "required": true,
            "schema": {
              "$ref": "#/definitions/authExchangeGoogleLoginRequest"
            }
          }
        ],
        "tags": [
          "AuthService"
        ]
      }
    },
    "/auth/v1/google/login": {
      "get": {
        "operationId": "AuthService_GoogleLogin",
        "responses": {
          "200": {
            "description": "A successful response.",
            "schema": {
              "$ref": "#/definitions/authGoogleLoginResponse"
            }
          },
          "default": {
            "description": "An unexpected error response.",
            "schema": {
              "$ref": "#/definitions/rpcStatus"
            }
          }
        },
        "parameters": [
          {
            "name": "redirectAfterLogin",
            "in": "query",
            "required": false,
            "type": "string"
          }
        ],
        "tags": [
          "AuthService"
        ]
      }
    },
    "/auth/v1/iam/permissions:check": {
      "post": {
        "operationId": "IAMService_CheckPermission",
        "responses": {
          "200": {
            "description": "A successful response.",
            "schema": {
              "$ref": "#/definitions/authCheckPermissionResponse"
            }
          },
          "default": {
            "description": "An unexpected error response.",
            "schema": {
              "$ref": "#/definitions/rpcStatus"
            }
          }
        },
        "parameters": [
          {
            "name": "body",
            "in": "body",
            "required": true,
            "schema": {
              "$ref": "#/definitions/authCheckPermissionRequest"
            }
          }
        ],
        "tags": [
          "IAMService"
        ]
      }
    },
    "/auth/v1/iam/platform-permissions:check": {
      "post": {
        "operationId": "IAMService_CheckPlatformPermission",
        "responses": {
          "200": {
            "description": "A successful response.",
            "schema": {
              "$ref": "#/definitions/authCheckPermissionResponse"
            }
          },
          "default": {
            "description": "An unexpected error response.",
            "schema": {
              "$ref": "#/definitions/rpcStatus"
            }
          }
        },
        "parameters": [
          {
            "name": "body",
            "in": "body",
            "required": true,
            "schema": {
              "$ref": "#/definitions/authCheckPlatformPermissionRequest"
            }
          }
        ],
        "tags": [
          "IAMService"
        ]
      }
    },
    "/auth/v1/iam/platform-users/{targetUserId}/roles": {
      "get": {
        "operationId": "IAMService_ListPlatformRoles",
        "responses": {
          "200": {
            "description": "A successful response.",
            "schema": {
              "$ref": "#/definitions/authListPlatformRolesResponse"
            }
          },
          "default": {
            "description": "An unexpected error response.",
            "schema": {
              "$ref": "#/definitions/rpcStatus"
            }
          }
        },
        "parameters": [
          {
            "name": "targetUserId",
            "in": "path",
            "required": true,
            "type": "string",
            "format": "uint64"
          },
          {
            "name": "actorUserId",
            "in": "query",
            "required": false,
            "type": "string",
            "format": "uint64"
          }
        ],
        "tags": [
          "IAMService"
        ]
      },
      "post": {
        "operationId": "IAMService_AddPlatformRole",
        "responses": {
          "200": {
            "description": "A successful response.",
            "schema": {
              "$ref": "#/definitions/authAddPlatformRoleResponse"
            }
          },
          "default": {
            "description": "An unexpected error response.",
            "schema": {
              "$ref": "#/definitions/rpcStatus"
            }
          }
        },
        "parameters": [
          {
            "name": "targetUserId",
            "in": "path",
            "required": true,
            "type": "string",
            "format": "uint64"
          },
          {
            "name": "body",
            "in": "body",
            "required": true,
            "schema": {
              "$ref": "#/definitions/IAMServiceAddPlatformRoleBody"
            }
          }
        ],
        "tags": [
          "IAMService"
        ]
      }
    },
    "/auth/v1/iam/platform-users/{targetUserId}/roles/{roleName}": {
      "delete": {
        "operationId": "IAMService_RemovePlatformRole",
        "responses": {
          "200": {
            "description": "A successful response.",
            "schema": {
              "$ref": "#/definitions/authRemovePlatformRoleResponse"
            }
          },
          "default": {
            "description": "An unexpected error response.",
            "schema": {
              "$ref": "#/definitions/rpcStatus"
            }
          }
        },
        "parameters": [
          {
            "name": "targetUserId",
            "in": "path",
            "required": true,
            "type": "string",
            "format": "uint64"
          },
          {
            "name": "roleName",
            "in": "path",
            "required": true,
            "type": "string"
          },
          {
            "name": "actorUserId",
            "in": "query",
            "required": false,
            "type": "string",
            "format": "uint64"
          }
        ],
        "tags": [
          "IAMService"
        ]
      }
    },
    "/auth/v1/iam/tenants": {
      "post": {
        "operationId": "IAMService_CreateTenant",
        "responses": {
          "200": {
            "description": "A successful response.",
            "schema": {
              "$ref": "#/definitions/authCreateTenantResponse"
            }
          },
          "default": {
            "description": "An unexpected error response.",
            "schema": {
              "$ref": "#/definitions/rpcStatus"
            }
          }
        },
        "parameters": [
          {
            "name": "body",
            "in": "body",
            "required": true,
            "schema": {
              "$ref": "#/definitions/authCreateTenantRequest"
            }
          }
        ],
        "tags": [
          "IAMService"
        ]
      }
    },
    "/auth/v1/iam/tenants/{tenantId}/members": {
      "get": {
        "operationId": "IAMService_ListTenantMembers",
        "responses": {
          "200": {
            "description": "A successful response.",
            "schema": {
              "$ref": "#/definitions/authListTenantMembersResponse"
            }
          },
          "default": {
            "description": "An unexpected error response.",
            "schema": {
              "$ref": "#/definitions/rpcStatus"
            }
          }
        },
        "parameters": [
          {
            "name": "tenantId",
            "in": "path",
            "required": true,
            "type": "string"
          }
        ],
        "tags": [
          "IAMService"
        ]
      },
      "post": {
        "operationId": "IAMService_AddTenantMember",
        "responses": {
          "200": {
            "description": "A successful response.",
            "schema": {
              "$ref": "#/definitions/authAddTenantMemberResponse"
            }
          },
          "default": {
            "description": "An unexpected error response.",
            "schema": {
              "$ref": "#/definitions/rpcStatus"
            }
          }
        },
        "parameters": [
          {
            "name": "tenantId",
            "in": "path",
            "required": true,
            "type": "string"
          },
          {
            "name": "body",
            "in": "body",
            "required": true,
            "schema": {
              "$ref": "#/definitions/IAMServiceAddTenantMemberBody"
            }
          }
        ],
        "tags": [
          "IAMService"
        ]
      }
    },
    "/auth/v1/iam/tenants/{tenantId}/members/{userId}": {
      "get": {
        "operationId": "IAMService_GetTenantMembership",
        "responses": {
          "200": {
            "description": "A successful response.",
            "schema": {
              "$ref": "#/definitions/authGetTenantMembershipResponse"
            }
          },
          "default": {
            "description": "An unexpected error response.",
            "schema": {
              "$ref": "#/definitions/rpcStatus"
            }
          }
        },
        "parameters": [
          {
            "name": "tenantId",
            "in": "path",
            "required": true,
            "type": "string"
          },
          {
            "name": "userId",
            "in": "path",
            "required": true,
            "type": "string",
            "format": "uint64"
          }
        ],
        "tags": [
          "IAMService"
        ]
      },
      "delete": {
        "operationId": "IAMService_RemoveTenantMember",
        "responses": {
          "200": {
            "description": "A successful response.",
            "schema": {
              "$ref": "#/definitions/authRemoveTenantMemberResponse"
            }
          },
          "default": {
            "description": "An unexpected error response.",
            "schema": {
              "$ref": "#/definitions/rpcStatus"
            }
          }
        },
        "parameters": [
          {
            "name": "tenantId",
            "in": "path",
            "required": true,
            "type": "string"
          },
          {
            "name": "userId",
            "in": "path",
            "required": true,
            "type": "string",
            "format": "uint64"
          }
        ],
        "tags": [
          "IAMService"
        ]
      }
    },
    "/auth/v1/iam/tenants:switch": {
      "post": {
        "operationId": "AuthService_SwitchActiveTenant",
        "responses": {
          "200": {
            "description": "A successful response.",
            "schema": {
              "$ref": "#/definitions/authSwitchActiveTenantResponse"
            }
          },
          "default": {
            "description": "An unexpected error response.",
            "schema": {
              "$ref": "#/definitions/rpcStatus"
            }
          }
        },
        "parameters": [
          {
            "name": "body",
            "in": "body",
            "required": true,
            "schema": {
              "$ref": "#/definitions/authSwitchActiveTenantRequest"
            }
          }
        ],
        "tags": [
          "AuthService"
        ]
      }
    },
    "/auth/v1/iam/users/{userId}/tenants": {
      "get": {
        "operationId": "IAMService_ListUserTenants",
        "responses": {
          "200": {
            "description": "A successful response.",
            "schema": {
              "$ref": "#/definitions/authListUserTenantsResponse"
            }
          },
          "default": {
            "description": "An unexpected error response.",
            "schema": {
              "$ref": "#/definitions/rpcStatus"
            }
          }
        },
        "parameters": [
          {
            "name": "userId",
            "in": "path",
            "required": true,
            "type": "string",
            "format": "uint64"
          }
        ],
        "tags": [
          "IAMService"
        ]
      }
    },
    "/auth/v1/login": {
      "post": {
        "operationId": "AuthService_Login",
        "responses": {
          "200": {
            "description": "A successful response.",
            "schema": {
              "$ref": "#/definitions/authLoginResponse"
            }
          },
          "default": {
            "description": "An unexpected error response.",
            "schema": {
              "$ref": "#/definitions/rpcStatus"
            }
          }
        },
        "parameters": [
          {
            "name": "body",
            "in": "body",
            "required": true,
            "schema": {
              "$ref": "#/definitions/authLoginRequest"
            }
          }
        ],
        "tags": [
          "AuthService"
        ]
      }
    },
    "/auth/v1/logout": {
      "post": {
        "operationId": "AuthService_Logout",
        "responses": {
          "200": {
            "description": "A successful response.",
            "schema": {
              "$ref": "#/definitions/authLogoutResponse"
            }
          },
          "default": {
            "description": "An unexpected error response.",
            "schema": {
              "$ref": "#/definitions/rpcStatus"
            }
          }
        },
        "parameters": [
          {
            "name": "body",
            "in": "body",
            "required": true,
            "schema": {
              "$ref": "#/definitions/authLogoutRequest"
            }
          }
        ],
        "tags": [
          "AuthService"
        ]
      }
    },
    "/auth/v1/refresh": {
      "post": {
        "operationId": "AuthService_RefreshToken",
        "responses": {
          "200": {
            "description": "A successful response.",
            "schema": {
              "$ref": "#/definitions/authRefreshTokenResponse"
            }
          },
          "default": {
            "description": "An unexpected error response.",
            "schema": {
              "$ref": "#/definitions/rpcStatus"
            }
          }
        },
        "parameters": [
          {
            "name": "body",
            "in": "body",
            "required": true,
            "schema": {
              "$ref": "#/definitions/authRefreshTokenRequest"
            }
          }
        ],
        "tags": [
          "AuthService"
        ]
      }
    },
    "/auth/v1/register": {
      "post": {
        "operationId": "AuthService_Register",
        "responses": {
          "200": {
            "description": "A successful response.",
            "schema": {
              "$ref": "#/definitions/authRegisterResponse"
            }
          },
          "default": {
            "description": "An unexpected error response.",
            "schema": {
              "$ref": "#/definitions/rpcStatus"
            }
          }
        },
        "parameters": [
          {
            "name": "body",
            "in": "body",
            "required": true,
            "schema": {
              "$ref": "#/definitions/authRegisterRequest"
            }
          }
        ],
        "tags": [
          "AuthService"
        ]
      }
    },
    "/auth/v1/sessions": {
      "get": {
        "operationId": "AuthService_ListSessions",
        "responses": {
          "200": {
            "description": "A successful response.",
            "schema": {
              "$ref": "#/definitions/authListSessionsResponse"
            }
          },
          "default": {
            "description": "An unexpected error response.",
            "schema": {
              "$ref": "#/definitions/rpcStatus"
            }
          }
        },
        "tags": [
          "AuthService"
        ]
      }
    },
    "/auth/v1/sessions/{sessionId}": {
      "get": {
        "operationId": "AuthService_GetSession",
        "responses": {
          "200": {
            "description": "A successful response.",
            "schema": {
              "$ref": "#/definitions/authGetSessionResponse"
            }
          },
          "default": {
            "description": "An unexpected error response.",
            "schema": {
              "$ref": "#/definitions/rpcStatus"
            }
          }
        },
        "parameters": [
          {
            "name": "sessionId",
            "in": "path",
            "required": true,
            "type": "string"
          }
        ],
        "tags": [
          "AuthService"
        ]
      },
      "delete": {
        "operationId": "AuthService_RevokeSession",
        "responses": {
          "200": {
            "description": "A successful response.",
            "schema": {
              "$ref": "#/definitions/authRevokeSessionResponse"
            }
          },
          "default": {
            "description": "An unexpected error response.",
            "schema": {
              "$ref": "#/definitions/rpcStatus"
            }
          }
        },
        "parameters": [
          {
            "name": "sessionId",
            "in": "path",
            "required": true,
            "type": "string"
          }
        ],
        "tags": [
          "AuthService"
        ]
      }
    }
  },
  "definitions": {
    "IAMServiceAddPlatformRoleBody": {
      "type": "object",
      "properties": {
        "actorUserId": {
          "type": "string",
          "format": "uint64"
        },
        "roleName": {
          "type": "string"
        }
      }
    },
    "IAMServiceAddTenantMemberBody": {
      "type": "object",
      "properties": {
        "userId": {
          "type": "string",
          "format": "uint64"
        },
        "roleName": {
          "type": "string"
        }
      }
    },
    "authAddPlatformRoleResponse": {
      "type": "object"
    },
    "authAddTenantMemberResponse": {
      "type": "object"
    },
    "authAuditLog": {
      "type": "object",
      "properties": {
        "id": {
          "type": "string"
        },
        "actorUserId": {
          "type": "string",
          "format": "uint64"
        },
        "action": {
          "type": "string"
        },
        "resourceType": {
          "type": "string"
        },
        "resourceId": {
          "type": "string"
        },
        "tenantId": {
          "type": "string"
        },
        "status": {
          "type": "string"
        },
        "payloadJson": {
          "type": "string"
        },
        "createdAt": {
          "type": "string"
        }
      }
    },
    "authCheckPermissionRequest": {
      "type": "object",
      "properties": {
        "tenantId": {
          "type": "string"
        },
        "userId": {
          "type": "string",
          "format": "uint64"
        },
        "permission": {
          "type": "string"
        }
      }
    },
    "authCheckPermissionResponse": {
      "type": "object",
      "properties": {
        "allowed": {
          "type": "boolean"
        }
      }
    },
    "authCheckPlatformPermissionRequest": {
      "type": "object",
      "properties": {
        "userId": {
          "type": "string",
          "format": "uint64"
        },
        "permission": {
          "type": "string"
        }
      }
    },
    "authCreateTenantRequest": {
      "type": "object",
      "properties": {
        "ownerUserId": {
          "type": "string",
          "format": "uint64"
        },
        "slug": {
          "type": "string"
        },
        "name": {
          "type": "string"
        }
      }
    },
    "authCreateTenantResponse": {
      "type": "object",
      "properties": {
        "tenant": {
          "$ref": "#/definitions/authTenant"
        },
        "ownerMembership": {
          "$ref": "#/definitions/authTenantMembership"
        }
      }
    },
    "authExchangeGoogleLoginRequest": {
      "type": "object",
      "properties": {
        "exchangeCode": {
          "type": "string"
        }
      }
    },
    "authGetSessionResponse": {
      "type": "object",
      "properties": {
        "session": {
          "$ref": "#/definitions/authSession"
        }
      }
    },
    "authGetTenantMembershipResponse": {
      "type": "object",
      "properties": {
        "membership": {
          "$ref": "#/definitions/authTenantMembership"
        }
      }
    },
    "authGoogleCallbackResponse": {
      "type": "object",
      "properties": {
        "exchangeCode": {
          "type": "string"
        },
        "redirectUrl": {
          "type": "string"
        },
        "userInfo": {
          "$ref": "#/definitions/authGoogleUserInfo"
        }
      }
    },
    "authGoogleLoginResponse": {
      "type": "object",
      "properties": {
        "redirectUrl": {
          "type": "string"
        }
      }
    },
    "authGoogleUserInfo": {
      "type": "object",
      "properties": {
        "id": {
          "type": "string"
        },
        "email": {
          "type": "string"
        },
        "name": {
          "type": "string"
        },
        "givenName": {
          "type": "string"
        },
        "familyName": {
          "type": "string"
        },
        "picture": {
          "type": "string"
        },
        "emailVerified": {
          "type": "boolean"
        }
      }
    },
    "authListAuditLogsResponse": {
      "type": "object",
      "properties": {
        "logs": {
          "type": "array",
          "items": {
            "type": "object",
            "$ref": "#/definitions/authAuditLog"
          }
        }
      }
    },
    "authListPlatformRolesResponse": {
      "type": "object",
      "properties": {
        "memberships": {
          "type": "array",
          "items": {
            "type": "object",
            "$ref": "#/definitions/authPlatformRoleMembership"
          }
        }
      }
    },
    "authListSessionsResponse": {
      "type": "object",
      "properties": {
        "sessions": {
          "type": "array",
          "items": {
            "type": "object",
            "$ref": "#/definitions/authSession"
          }
        }
      }
    },
    "authListTenantMembersResponse": {
      "type": "object",
      "properties": {
        "memberships": {
          "type": "array",
          "items": {
            "type": "object",
            "$ref": "#/definitions/authTenantMembership"
          }
        }
      }
    },
    "authListUserTenantsResponse": {
      "type": "object",
      "properties": {
        "memberships": {
          "type": "array",
          "items": {
            "type": "object",
            "$ref": "#/definitions/authTenantMembership"
          }
        }
      }
    },
    "authLoginRequest": {
      "type": "object",
      "properties": {
        "username": {
          "type": "string"
        },
        "password": {
          "type": "string"
        }
      }
    },
    "authLoginResponse": {
      "type": "object",
      "properties": {
        "jwtToken": {
          "type": "string"
        },
        "userInfo": {
          "$ref": "#/definitions/authUserInfo"
        },
        "refreshToken": {
          "type": "string"
        }
      }
    },
    "authLogoutRequest": {
      "type": "object",
      "properties": {
        "token": {
          "type": "string"
        }
      }
    },
    "authLogoutResponse": {
      "type": "object",
      "properties": {
        "success": {
          "type": "boolean"
        },
        "redirectUrl": {
          "type": "string"
        }
      }
    },
    "authPlatformRoleMembership": {
      "type": "object",
      "properties": {
        "userId": {
          "type": "string",
          "format": "uint64"
        },
        "roleId": {
          "type": "string",
          "format": "uint64"
        },
        "roleName": {
          "type": "string"
        },
        "status": {
          "type": "string"
        },
        "createdAt": {
          "type": "string"
        },
        "updatedAt": {
          "type": "string"
        }
      }
    },
    "authRefreshTokenRequest": {
      "type": "object",
      "properties": {
        "refreshToken": {
          "type": "string"
        }
      }
    },
    "authRefreshTokenResponse": {
      "type": "object",
      "properties": {
        "jwtToken": {
          "type": "string"
        },
        "userInfo": {
          "$ref": "#/definitions/authUserInfo"
        },
        "refreshToken": {
          "type": "string"
        }
      }
    },
    "authRegisterRequest": {
      "type": "object",
      "properties": {
        "username": {
          "type": "string"
        },
        "password": {
          "type": "string"
        },
        "email": {
          "type": "string"
        }
      }
    },
    "authRegisterResponse": {
      "type": "object",
      "properties": {
        "jwtToken": {
          "type": "string"
        },
        "userInfo": {
          "$ref": "#/definitions/authUserInfo"
        },
        "refreshToken": {
          "type": "string"
        }
      }
    },
    "authRemovePlatformRoleResponse": {
      "type": "object"
    },
    "authRemoveTenantMemberResponse": {
      "type": "object"
    },
    "authRevokeSessionResponse": {
      "type": "object"
    },
    "authSession": {
      "type": "object",
      "properties": {
        "id": {
          "type": "string"
        },
        "userId": {
          "type": "string",
          "format": "uint64"
        },
        "activeTenantId": {
          "type": "string"
        },
        "status": {
          "type": "string"
        },
        "createdAt": {
          "type": "string"
        },
        "updatedAt": {
          "type": "string"
        },
        "expiresAt": {
          "type": "string"
        },
        "revokedAt": {
          "type": "string"
        }
      }
    },
    "authSwitchActiveTenantRequest": {
      "type": "object",
      "properties": {
        "userId": {
          "type": "string",
          "format": "uint64"
        },
        "tenantId": {
          "type": "string"
        },
        "accessToken": {
          "type": "string"
        }
      }
    },
    "authSwitchActiveTenantResponse": {
      "type": "object",
      "properties": {
        "jwtToken": {
          "type": "string"
        },
        "userInfo": {
          "$ref": "#/definitions/authUserInfo"
        },
        "refreshToken": {
          "type": "string"
        }
      }
    },
    "authTenant": {
      "type": "object",
      "properties": {
        "id": {
          "type": "string"
        },
        "slug": {
          "type": "string"
        },
        "name": {
          "type": "string"
        },
        "createdAt": {
          "type": "string"
        },
        "updatedAt": {
          "type": "string"
        }
      }
    },
    "authTenantMembership": {
      "type": "object",
      "properties": {
        "tenantId": {
          "type": "string"
        },
        "userId": {
          "type": "string",
          "format": "uint64"
        },
        "roleId": {
          "type": "string",
          "format": "uint64"
        },
        "roleName": {
          "type": "string"
        },
        "status": {
          "type": "string"
        },
        "createdAt": {
          "type": "string"
        },
        "updatedAt": {
          "type": "string"
        }
      }
    },
    "authUserInfo": {
      "type": "object",
      "properties": {
        "id": {
          "type": "integer",
          "format": "int32"
        },
        "email": {
          "type": "string"
        },
        "username": {
          "type": "string"
        },
        "fullName": {
          "type": "string"
        },
        "middleName": {
          "type": "string"
        },
        "firstName": {
          "type": "string"
        },
        "lastName": {
          "type": "string"
        },
        "address": {
          "type": "string"
        },
        "initialFrom": {
          "type": "string"
        },
        "age": {
          "type": "integer",
          "format": "int32"
        },
        "dob": {
          "type": "string"
        },
        "emailVerified": {
          "type": "boolean"
        }
      }
    },
    "protobufAny": {
      "type": "object",
      "properties": {
        "@type": {
          "type": "string"
        }
      },
      "additionalProperties": {}
    },
    "rpcStatus": {
      "type": "object",
      "properties": {
        "code": {
          "type": "integer",
          "format": "int32"
        },
        "message": {
          "type": "string"
        },
        "details": {
          "type": "array",
          "items": {
            "type": "object",
            "$ref": "#/definitions/protobufAny"
          }
        }
      }
    }
  }
}
